jupyterlab_telemetry_producer/__init__.py
jupyterlab_telemetry_producer/_version.py
jupyterlab_telemetry_producer/application.py
jupyterlab_telemetry_producer/handlers.py
jupyterlab_telemetry_producer-0.1.7.data/data/etc/jupyter/jupyter_server_config.d/jupyterlab_telemetry_producer.json
jupyterlab_telemetry_producer-0.1.7.data/data/share/jupyter/labextensions/jupyterlab-telemetry-producer/package.json
jupyterlab_telemetry_producer-0.1.7.data/data/share/jupyter/labextensions/jupyterlab-telemetry-producer/static/747.5264005781d930c4cc68.js
jupyterlab_telemetry_producer-0.1.7.data/data/share/jupyter/labextensions/jupyterlab-telemetry-producer/static/8.a0b6a218b41baaa01c41.js
jupyterlab_telemetry_producer-0.1.7.data/data/share/jupyter/labextensions/jupyterlab-telemetry-producer/static/remoteEntry.d59a99f9ead196b57b70.js
jupyterlab_telemetry_producer-0.1.7.data/data/share/jupyter/labextensions/jupyterlab-telemetry-producer/static/style.js
jupyterlab_telemetry_producer-0.1.7.data/data/share/jupyter/labextensions/jupyterlab-telemetry-producer/static/third-party-licenses.json
jupyterlab_telemetry_producer-0.1.7.data/data/share/jupyter/labextensions/jupyterlab-telemetry-producer/install.json
jupyterlab_telemetry_producer-0.1.7.dist-info/METADATA
jupyterlab_telemetry_producer-0.1.7.dist-info/WHEEL
jupyterlab_telemetry_producer-0.1.7.dist-info/licenses/LICENSE
jupyterlab_telemetry_producer-0.1.7.dist-info/RECORD
